<?xml version="1.0" encoding="UTF-8" ?><patterns>		<pattern id="1" diac="آعٍ" canonic="فاعٍ" type="فا" cas="نك" ncg="1"/>
		<pattern id="10412" diac="فَعُّ" canonic="فَعُّ" type="جا" cas="إض" ncg="1"/>
		<pattern id="10413" diac="فَعُّ" canonic="فَعُّ" type="جا" cas="إض" ncg="5"/>
		<pattern id="10414" diac="فَعُّ" canonic="فَعُّ" type="صأ" cas="إض" ncg="1"/>
		<pattern id="10415" diac="فَعُّ" canonic="فَعُّ" type="فض" cas="إض" ncg="1"/>
		<pattern id="10416" diac="فَعُّ" canonic="فَعُّ" type="فض" cas="إض" ncg="2"/>
		<pattern id="10417" diac="فَعُّ" canonic="فَعُّ" type="فض" cas="إض" ncg="3"/>
		<pattern id="10418" diac="فَعُّ" canonic="فَعُّ" type="فض" cas="إض" ncg="4"/>
		<pattern id="10419" diac="فَعُّ" canonic="فَعُّ" type="فض" cas="إض" ncg="5"/>
		<pattern id="10420" diac="فَعُّ" canonic="فَعُّ" type="فض" cas="إض" ncg="6"/>
		<pattern id="10421" diac="فَعُّ" canonic="فَعُّ" type="فض" cas="نك" ncg="1"/>
		<pattern id="10422" diac="فَعُّ" canonic="فَعُّ" type="فض" cas="نك" ncg="2"/>
		<pattern id="10423" diac="فَعُّ" canonic="فَعُّ" type="فض" cas="نك" ncg="3"/>
		<pattern id="10424" diac="فَعُّ" canonic="فَعُّ" type="فض" cas="نك" ncg="4"/>
		<pattern id="10425" diac="فَعُّ" canonic="فَعُّ" type="فض" cas="نك" ncg="5"/>
		<pattern id="10426" diac="فَعُّ" canonic="فَعُّ" type="فض" cas="نك" ncg="6"/>
		<pattern id="10427" diac="فَعُّ" canonic="فَعُّ" type="وش" cas="إض" ncg="1"/>
		<pattern id="10538" diac="فَعِّ" canonic="فَعِّ" type="جا" cas="إض" ncg="13"/>
		<pattern id="10539" diac="فَعِّ" canonic="فَعِّ" type="جا" cas="إض" ncg="17"/>
		<pattern id="10540" diac="فَعِّ" canonic="فَعِّ" type="صأ" cas="إض" ncg="13"/>
		<pattern id="10541" diac="فَعِّ" canonic="فَعِّ" type="فض" cas="إض" ncg="13"/>
		<pattern id="10542" diac="فَعِّ" canonic="فَعِّ" type="فض" cas="إض" ncg="14"/>
		<pattern id="10543" diac="فَعِّ" canonic="فَعِّ" type="فض" cas="إض" ncg="15"/>
		<pattern id="10544" diac="فَعِّ" canonic="فَعِّ" type="فض" cas="إض" ncg="16"/>
		<pattern id="10545" diac="فَعِّ" canonic="فَعِّ" type="فض" cas="إض" ncg="17"/>
		<pattern id="10546" diac="فَعِّ" canonic="فَعِّ" type="فض" cas="نك" ncg="13"/>
		<pattern id="10547" diac="فَعِّ" canonic="فَعِّ" type="فض" cas="نك" ncg="14"/>
		<pattern id="10548" diac="فَعِّ" canonic="فَعِّ" type="فض" cas="نك" ncg="15"/>
		<pattern id="10549" diac="فَعِّ" canonic="فَعِّ" type="فض" cas="نك" ncg="16"/>
		<pattern id="10550" diac="فَعِّ" canonic="فَعِّ" type="فض" cas="نك" ncg="17"/>
		<pattern id="10551" diac="فَعِّ" canonic="فَعِّ" type="وش" cas="إض" ncg="13"/>
		<pattern id="14261" diac="فُعٌّ" canonic="فُعٌّ" type="جا" cas="نك" ncg="1"/>
		<pattern id="14262" diac="فُعٌّ" canonic="فُعٌّ" type="جا" cas="نك" ncg="5"/>
		<pattern id="14263" diac="فُعٌّ" canonic="فُعٌّ" type="جا" cas="نك" ncg="6"/>
		<pattern id="14264" diac="فُعٌّ" canonic="فُعٌّ" type="صأ" cas="نك" ncg="1"/>
		<pattern id="14265" diac="فُعٍّ" canonic="فُعٍّ" type="جا" cas="نك" ncg="13"/>
		<pattern id="14266" diac="فُعٍّ" canonic="فُعٍّ" type="جا" cas="نك" ncg="17"/>
		<pattern id="14267" diac="فُعٍّ" canonic="فُعٍّ" type="جا" cas="نك" ncg="18"/>
		<pattern id="14268" diac="فُعٍّ" canonic="فُعٍّ" type="صأ" cas="نك" ncg="13"/>
		<pattern id="14269" diac="فُعَّ" canonic="فُعَّ" type="جا" cas="إض" ncg="11"/>
		<pattern id="14270" diac="فُعَّ" canonic="فُعَّ" type="جا" cas="إض" ncg="12"/>
		<pattern id="14271" diac="فُعَّ" canonic="فُعَّ" type="جا" cas="إض" ncg="18"/>
		<pattern id="14272" diac="فُعَّ" canonic="فُعَّ" type="جا" cas="إض" ncg="7"/>
		<pattern id="14273" diac="فُعَّ" canonic="فُعَّ" type="صأ" cas="إض" ncg="7"/>
		<pattern id="14705" diac="فُعُّ" canonic="فُعُّ" type="جا" cas="إض" ncg="1"/>
		<pattern id="14706" diac="فُعُّ" canonic="فُعُّ" type="جا" cas="إض" ncg="5"/>
		<pattern id="14707" diac="فُعُّ" canonic="فُعُّ" type="جا" cas="إض" ncg="6"/>
		<pattern id="14708" diac="فُعُّ" canonic="فُعُّ" type="صأ" cas="إض" ncg="1"/>
		<pattern id="14709" diac="فُعِّ" canonic="فُعِّ" type="جا" cas="إض" ncg="13"/>
		<pattern id="14710" diac="فُعِّ" canonic="فُعِّ" type="جا" cas="إض" ncg="17"/>
		<pattern id="14711" diac="فُعِّ" canonic="فُعِّ" type="جا" cas="إض" ncg="18"/>
		<pattern id="14712" diac="فُعِّ" canonic="فُعِّ" type="صأ" cas="إض" ncg="13"/>
		<pattern id="16975" diac="فِعٌّ" canonic="فِعٌّ" type="جا" cas="نك" ncg="1"/>
		<pattern id="16976" diac="فِعٌّ" canonic="فِعٌّ" type="صأ" cas="نك" ncg="1"/>
		<pattern id="16977" diac="فِعٍّ" canonic="فِعٍّ" type="جا" cas="نك" ncg="13"/>
		<pattern id="16978" diac="فِعٍّ" canonic="فِعٍّ" type="صأ" cas="نك" ncg="13"/>
		<pattern id="16979" diac="فِعَّ" canonic="فِعَّ" type="جا" cas="إض" ncg="7"/>
		<pattern id="16980" diac="فِعَّ" canonic="فِعَّ" type="صأ" cas="إض" ncg="7"/>
		<pattern id="17149" diac="فِعُّ" canonic="فِعُّ" type="جا" cas="إض" ncg="1"/>
		<pattern id="17150" diac="فِعُّ" canonic="فِعُّ" type="صأ" cas="إض" ncg="1"/>
		<pattern id="17151" diac="فِعِّ" canonic="فِعِّ" type="جا" cas="إض" ncg="13"/>
		<pattern id="17152" diac="فِعِّ" canonic="فِعِّ" type="صأ" cas="إض" ncg="13"/>
		<pattern id="2" diac="آعٍ" canonic="فاعٍ" type="فا" cas="نك" ncg="13"/>
		<pattern id="4038" diac="فعٌ" canonic="فعٌ" type="جا" cas="نك" ncg="1"/>
		<pattern id="4039" diac="فعٍ" canonic="فعٍ" type="جا" cas="نك" ncg="13"/>
		<pattern id="4040" diac="فعٍ" canonic="فعٍ" type="وش" cas="نك" ncg="1"/>
		<pattern id="4041" diac="فعٍ" canonic="فعٍ" type="وش" cas="نك" ncg="13"/>
		<pattern id="4042" diac="فعَ" canonic="فعَ" type="جا" cas="إض" ncg="7"/>
		<pattern id="4730" diac="فعُ" canonic="فعُ" type="جا" cas="إض" ncg="1"/>
		<pattern id="4827" diac="فعِ" canonic="فعِ" type="جا" cas="إض" ncg="13"/>
		<pattern id="501" diac="آلٌ" canonic="فالٌ" type="جا" cas="نك" ncg="1"/>
		<pattern id="502" diac="آلٌ" canonic="فالٌ" type="جا" cas="نك" ncg="6"/>
		<pattern id="503" diac="آلٌ" canonic="فالٌ" type="صأ" cas="نك" ncg="1"/>
		<pattern id="504" diac="آلٍ" canonic="فالٍ" type="جا" cas="نك" ncg="13"/>
		<pattern id="505" diac="آلٍ" canonic="فالٍ" type="جا" cas="نك" ncg="18"/>
		<pattern id="506" diac="آلٍ" canonic="فالٍ" type="صأ" cas="نك" ncg="13"/>
		<pattern id="507" diac="آلَ" canonic="فالَ" type="جا" cas="إض" ncg="12"/>
		<pattern id="508" diac="آلَ" canonic="فالَ" type="جا" cas="إض" ncg="18"/>
		<pattern id="509" diac="آلَ" canonic="فالَ" type="جا" cas="إض" ncg="7"/>
		<pattern id="510" diac="آلَ" canonic="فالَ" type="صأ" cas="إض" ncg="7"/>
		<pattern id="5181" diac="فعٌّ" canonic="فعٌّ" type="جا" cas="نك" ncg="1"/>
		<pattern id="5182" diac="فعٌّ" canonic="فعٌّ" type="جا" cas="نك" ncg="5"/>
		<pattern id="5183" diac="فعٌّ" canonic="فعٌّ" type="صأ" cas="نك" ncg="1"/>
		<pattern id="5184" diac="فعٍّ" canonic="فعٍّ" type="جا" cas="نك" ncg="13"/>
		<pattern id="5185" diac="فعٍّ" canonic="فعٍّ" type="جا" cas="نك" ncg="17"/>
		<pattern id="5186" diac="فعٍّ" canonic="فعٍّ" type="صأ" cas="نك" ncg="13"/>
		<pattern id="5187" diac="فعَّ" canonic="فعَّ" type="جا" cas="إض" ncg="11"/>
		<pattern id="5188" diac="فعَّ" canonic="فعَّ" type="جا" cas="إض" ncg="7"/>
		<pattern id="5189" diac="فعَّ" canonic="فعَّ" type="صأ" cas="إض" ncg="7"/>
		<pattern id="5346" diac="فعُّ" canonic="فعُّ" type="جا" cas="إض" ncg="1"/>
		<pattern id="5347" diac="فعُّ" canonic="فعُّ" type="جا" cas="إض" ncg="5"/>
		<pattern id="5348" diac="فعُّ" canonic="فعُّ" type="صأ" cas="إض" ncg="1"/>
		<pattern id="5349" diac="فعِّ" canonic="فعِّ" type="جا" cas="إض" ncg="13"/>
		<pattern id="5350" diac="فعِّ" canonic="فعِّ" type="جا" cas="إض" ncg="17"/>
		<pattern id="5351" diac="فعِّ" canonic="فعِّ" type="صأ" cas="إض" ncg="13"/>
		<pattern id="569" diac="آلُ" canonic="فالُ" type="جا" cas="إض" ncg="1"/>
		<pattern id="570" diac="آلُ" canonic="فالُ" type="جا" cas="إض" ncg="6"/>
		<pattern id="571" diac="آلُ" canonic="فالُ" type="صأ" cas="إض" ncg="1"/>
		<pattern id="572" diac="آلِ" canonic="فالِ" type="جا" cas="إض" ncg="13"/>
		<pattern id="573" diac="آلِ" canonic="فالِ" type="جا" cas="إض" ncg="18"/>
		<pattern id="574" diac="آلِ" canonic="فالِ" type="صأ" cas="إض" ncg="13"/>
		<pattern id="7113" diac="فَعٌ" canonic="فَعٌ" type="جا" cas="نك" ncg="1"/>
		<pattern id="7114" diac="فَعٍ" canonic="فَعٍ" type="جا" cas="نك" ncg="13"/>
		<pattern id="7115" diac="فَعٍ" canonic="فَعٍ" type="مفا" cas="نك" ncg="1"/>
		<pattern id="7116" diac="فَعٍ" canonic="فَعٍ" type="مفا" cas="نك" ncg="13"/>
		<pattern id="7117" diac="فَعٍ" canonic="فَعٍ" type="وش" cas="نك" ncg="1"/>
		<pattern id="7118" diac="فَعٍ" canonic="فَعٍ" type="وش" cas="نك" ncg="13"/>
		<pattern id="7119" diac="فَعَ" canonic="فَعَ" type="جا" cas="إض" ncg="7"/>
		<pattern id="8826" diac="فَعُ" canonic="فَعُ" type="جا" cas="إض" ncg="1"/>
		<pattern id="9157" diac="فَعِ" canonic="فَعِ" type="جا" cas="إض" ncg="13"/>
		<pattern id="9840" diac="فَعٌّ" canonic="فَعٌّ" type="جا" cas="نك" ncg="1"/>
		<pattern id="9841" diac="فَعٌّ" canonic="فَعٌّ" type="جا" cas="نك" ncg="5"/>
		<pattern id="9842" diac="فَعٌّ" canonic="فَعٌّ" type="صأ" cas="نك" ncg="1"/>
		<pattern id="9843" diac="فَعٌّ" canonic="فَعٌّ" type="وش" cas="نك" ncg="1"/>
		<pattern id="9844" diac="فَعٍّ" canonic="فَعٍّ" type="جا" cas="نك" ncg="13"/>
		<pattern id="9845" diac="فَعٍّ" canonic="فَعٍّ" type="جا" cas="نك" ncg="17"/>
		<pattern id="9846" diac="فَعٍّ" canonic="فَعٍّ" type="صأ" cas="نك" ncg="13"/>
		<pattern id="9847" diac="فَعٍّ" canonic="فَعٍّ" type="وش" cas="نك" ncg="13"/>
		<pattern id="9848" diac="فَعَّ" canonic="فَعَّ" type="جا" cas="إض" ncg="11"/>
		<pattern id="9849" diac="فَعَّ" canonic="فَعَّ" type="جا" cas="إض" ncg="7"/>
		<pattern id="9850" diac="فَعَّ" canonic="فَعَّ" type="صأ" cas="إض" ncg="7"/>
		<pattern id="9851" diac="فَعَّ" canonic="فَعَّ" type="فض" cas="إض" ncg="10"/>
		<pattern id="9852" diac="فَعَّ" canonic="فَعَّ" type="فض" cas="إض" ncg="11"/>
		<pattern id="9853" diac="فَعَّ" canonic="فَعَّ" type="فض" cas="إض" ncg="12"/>
		<pattern id="9854" diac="فَعَّ" canonic="فَعَّ" type="فض" cas="إض" ncg="18"/>
		<pattern id="9855" diac="فَعَّ" canonic="فَعَّ" type="فض" cas="إض" ncg="7"/>
		<pattern id="9856" diac="فَعَّ" canonic="فَعَّ" type="فض" cas="إض" ncg="8"/>
		<pattern id="9857" diac="فَعَّ" canonic="فَعَّ" type="فض" cas="إض" ncg="9"/>
		<pattern id="9858" diac="فَعَّ" canonic="فَعَّ" type="فض" cas="نك" ncg="10"/>
		<pattern id="9859" diac="فَعَّ" canonic="فَعَّ" type="فض" cas="نك" ncg="11"/>
		<pattern id="9860" diac="فَعَّ" canonic="فَعَّ" type="فض" cas="نك" ncg="12"/>
		<pattern id="9861" diac="فَعَّ" canonic="فَعَّ" type="فض" cas="نك" ncg="18"/>
		<pattern id="9862" diac="فَعَّ" canonic="فَعَّ" type="فض" cas="نك" ncg="7"/>
		<pattern id="9863" diac="فَعَّ" canonic="فَعَّ" type="فض" cas="نك" ncg="8"/>
		<pattern id="9864" diac="فَعَّ" canonic="فَعَّ" type="فض" cas="نك" ncg="9"/>
		<pattern id="9865" diac="فَعَّ" canonic="فَعَّ" type="وش" cas="إض" ncg="7"/></patterns>
